ponto/__init__.py
ponto/__main__.py
ponto/cli.py
ponto/configuration.py
ponto/drive.py
ponto/paths.py
ponto/scm.py
ponto/utils.py
ponto-0.0.3.dist-info/DESCRIPTION.rst
ponto-0.0.3.dist-info/METADATA
ponto-0.0.3.dist-info/RECORD
ponto-0.0.3.dist-info/WHEEL
ponto-0.0.3.dist-info/entry_points.txt
ponto-0.0.3.dist-info/metadata.json
ponto-0.0.3.dist-info/top_level.txt
