Metadata-Version: 2.0
Name: ponto
Version: 0.0.3
Summary: Backup Manager
Home-page: https://github.com/jmcs/ponto
Author: João Santos
Author-email: jmcs@jsantos.eu
License: MIT License
Platform: UNKNOWN
Classifier: Programming Language :: Python
Classifier: Programming Language :: Python :: 3.5
Classifier: Development Status :: 4 - Beta
Classifier: Operating System :: OS Independent
Requires-Dist: click
Requires-Dist: clickclick
Requires-Dist: pathlib
Requires-Dist: pip
Requires-Dist: requests
